{
  "id": "2652767763_2",
  "title": "28岁球星若塔车祸死亡，十天前刚与青梅竹马完婚",
  "content": "<div class=\"rich_media_content js_underline_content autoTypeSetting24psection\" id=\"js_content\">\n <section data-pm-slice=\"0 0 []\" style=\"margin-left: 8px;margin-right: 8px;\">\n  <section>\n   <span leaf=\"\">\n    <img alt=\"图片\" class=\"rich_pages wxw-img\" data-imgfileid=\"504488306\" data-ratio=\"0.09259259259259259\" data-s=\"300,640\" data-type=\"png\" data-w=\"1080\" src=\"/static/res/logo/https://mmbiz.qpic.cn/mmbiz_png/BIH6m4FJcJkk0zxaFtDkTic4ql3NJrddcQGalJpCTKAzwe3Kfzzmc5mmmHBkf28BE1WursGvzq4ySSLOXwJSiaxQ/640?wx_fmt=png&amp;tp=webp&amp;wxfrom=5&amp;wx_lazy=1\" style=\"-webkit-tap-highlight-color: transparent;margin-top: 0px;margin-bottom: 0px;padding: 0px;outline: 0px;max-width: 100%;vertical-align: bottom;box-sizing: border-box !important;overflow-wrap: break-word !important;height: auto !important;visibility: visible !important;width: 1080px !important;\"/>\n   </span>\n  </section>\n  <section>\n   <section data-autoskip=\"1\" data-pm-slice='4 11 [\"para\",{\"tagName\":\"section\",\"attributes\":{\"style\":\"line-height: 1.75em;margin: 0px 8px;\",\"data-pm-slice\":\"0 0 []\"},\"namespaceURI\":\"http://www.w3.org/1999/xhtml\"},\"para\",{\"tagName\":\"section\",\"attributes\":{},\"namespaceURI\":\"http://www.w3.org/1999/xhtml\"}]' deep=\"10\">\n    <section data-mpa-action-id=\"mcn63e1a1gkb\" data-pm-slice=\"0 0 []\" style='-webkit-tap-highlight-color: transparent;margin-top: 0px;margin-bottom: 0px;padding: 0px;outline: 0px;max-width: 100%;color: rgba(0, 0, 0, 0.9);font-family: \"PingFang SC\", system-ui, -apple-system, BlinkMacSystemFont, \"Helvetica Neue\", \"Hiragino Sans GB\", \"Microsoft YaHei UI\", \"Microsoft YaHei\", Arial, sans-serif;font-size: 17px;font-style: normal;font-variant-ligatures: normal;font-variant-caps: normal;font-weight: 400;letter-spacing: 0.544px;orphans: 2;text-indent: 0px;text-transform: none;widows: 2;word-spacing: 0px;-webkit-text-stroke-width: 0px;white-space: normal;background-color: rgb(255, 255, 255);text-decoration-thickness: initial;text-decoration-style: initial;text-decoration-color: initial;text-align: center;line-height: 1.75em;visibility: visible;box-sizing: border-box !important;overflow-wrap: break-word !important;'>\n     <p data-pm-slice=\"0 0 []\" style=\"margin-bottom: 0px;line-height: 1.75em;text-align: justify;\">\n      <span leaf=\"\" style=\"font-size: 16px;\">\n       <br/>\n      </span>\n     </p>\n     <p data-pm-slice=\"0 0 []\" style=\"margin-bottom: 0px;line-height: 1.75em;text-align: justify;\">\n      <span leaf=\"\" style=\"font-size: 16px;\">\n       <span style=\"letter-spacing: 1px;\" textstyle=\"\">\n        据多家外媒报道，效力于英超联赛利物浦俱乐部的葡萄牙籍球星迪奥戈·若塔在一起车祸事故中丧生。\n       </span>\n      </span>\n     </p>\n     <p style=\"margin-bottom: 0px;line-height: 1.75em;text-align: justify;\">\n      <span leaf=\"\" style=\"font-size: 16px;\">\n       <br/>\n      </span>\n     </p>\n     <section data-mpa-action-id=\"mcn64chmmom\" data-pm-slice=\"0 0 []\" nodeleaf=\"\">\n      <img alt=\"图片\" class=\"rich_pages wxw-img js_insertlocalimg\" data-backh=\"978\" data-backw=\"578\" data-imgfileid=\"100058695\" data-ratio=\"1.6916666666666667\" data-s=\"300,640\" data-type=\"jpeg\" data-w=\"1080\" src=\"/static/res/logo/https://mmbiz.qpic.cn/mmbiz_jpg/A9b5Jxh1w2EMEZs7Epnibl3EbFkVPdvDwVHBZPhXZsyN4htc3xXiaGuHWhWtCm3koOILPm7AIhWPGypqgkFV2JbA/640?wx_fmt=jpeg&amp;from=appmsg&amp;tp=wxpic&amp;wxfrom=5&amp;wx_lazy=1\" style=\"width: 1080px !important;height: auto !important;visibility: visible !important;border-style: solid;border-width: 1080px;\" type=\"block\"/>\n     </section>\n     <p style=\"margin-bottom: 0px;line-height: 1.75em;text-align: justify;\">\n      <span leaf=\"\" style=\"font-size: 16px;\">\n       <br/>\n      </span>\n     </p>\n     <p style=\"margin-bottom: 0px;line-height: 1.75em;text-align: justify;\">\n      <span leaf=\"\" style=\"font-size: 16px;\">\n       <span style=\"letter-spacing: 1px;\" textstyle=\"\">\n        BBC报道称，事故发生在西班牙萨莫拉。当地时间7月3日凌晨，若塔所乘车辆在试图超车时因轮胎爆裂而偏离了公路，随后车辆起火。意外发生时，若塔的弟弟也在车上，后者也被证实已经死亡。\n       </span>\n      </span>\n     </p>\n     <p style=\"margin-bottom: 0px;line-height: 1.75em;text-align: justify;\">\n      <span leaf=\"\" style=\"font-size: 16px;\">\n       <br/>\n      </span>\n     </p>\n     <p style=\"margin-bottom: 0px;line-height: 1.75em;text-align: justify;\">\n      <span leaf=\"\" style=\"font-size: 16px;\">\n       <span style=\"letter-spacing: 1px;\" textstyle=\"\">\n        资料显示，若塔1996年12月4日出生于葡萄牙波尔图，还不满29岁的他正值职业生涯黄金期。作为多面攻击手，若塔能胜任前场多个位置，可边可中。\n       </span>\n      </span>\n     </p>\n     <p style=\"margin-bottom: 0px;line-height: 1.75em;text-align: justify;\">\n      <span leaf=\"\" style=\"font-size: 16px;\">\n       <br/>\n      </span>\n     </p>\n     <section nodeleaf=\"\" style=\"margin-bottom: 0px;line-height: 1.75em;text-align: justify;\">\n      <span style=\"letter-spacing: 1px;\" textstyle=\"\">\n       <img alt=\"图片\" class=\"rich_pages wxw-img js_insertlocalimg\" data-backh=\"386\" data-backw=\"578\" data-imgfileid=\"100058694\" data-ratio=\"0.6671428571428571\" data-s=\"300,640\" data-type=\"jpeg\" data-w=\"700\" src=\"/static/res/logo/https://mmbiz.qpic.cn/mmbiz_jpg/A9b5Jxh1w2EMEZs7Epnibl3EbFkVPdvDwgliaAyD2KE3Othe10F2yUeNdVxqk0YWutLb7dX3B7Y9VzUFsUDib71bg/640?wx_fmt=jpeg&amp;from=appmsg&amp;tp=wxpic&amp;wxfrom=5&amp;wx_lazy=1\" style=\"width: 1080px !important;height: auto !important;visibility: visible !important;\" type=\"block\"/>\n      </span>\n     </section>\n     <p style=\"margin-bottom: 0px;line-height: 1.75em;text-align: center;\">\n      <span style=\"font-size: 16px;\">\n       <span mpa-font-style=\"mcn63e101b43\" style=\"letter-spacing: 1px;font-size: 12px;\">\n        <span leaf=\"\">\n         <span style=\"color: rgb(136, 136, 136);\" textstyle=\"\">\n          资料图：若塔在比赛中 图片来源：视觉中国\n         </span>\n        </span>\n       </span>\n      </span>\n     </p>\n     <p style=\"margin-bottom: 0px;line-height: 1.75em;text-align: justify;\">\n      <span leaf=\"\" style=\"font-size: 16px;\">\n       <br/>\n      </span>\n     </p>\n     <p style=\"margin-bottom: 0px;line-height: 1.75em;text-align: justify;\">\n      <span leaf=\"\" style=\"font-size: 16px;\">\n       <span style=\"letter-spacing: 1px;\" textstyle=\"\">\n        2016年夏天，若塔转会至马德里竞技，随后被租借至波尔图。一年后，若塔被狼队以先租后买的形式引进，登陆英格兰赛场的他开始被更多球迷所知。\n       </span>\n      </span>\n     </p>\n     <p style=\"margin-bottom: 0px;line-height: 1.75em;text-align: justify;\">\n      <span leaf=\"\" style=\"font-size: 16px;\">\n       <br/>\n      </span>\n     </p>\n     <p style=\"margin-bottom: 0px;line-height: 1.75em;text-align: justify;\">\n      <span leaf=\"\" style=\"font-size: 16px;\">\n       <span style=\"letter-spacing: 1px;\" textstyle=\"\">\n        2020年9月，若塔转会加盟英超豪门利物浦，迈上生涯新台阶。数据统计显示，过去五个赛季中，虽然多次遭遇伤病问题，但若塔仍为利物浦出场182次，奉献65粒进球和26次助攻，随队获得英超联赛冠军、足总杯冠军、联赛杯冠军等荣誉。\n       </span>\n      </span>\n     </p>\n     <p style=\"margin-bottom: 0px;line-height: 1.75em;text-align: justify;\">\n      <span leaf=\"\" style=\"font-size: 16px;\">\n       <br/>\n      </span>\n     </p>\n     <section nodeleaf=\"\" style=\"margin-bottom: 0px;line-height: 1.75em;text-align: justify;\">\n      <img alt=\"图片\" class=\"rich_pages wxw-img js_insertlocalimg\" data-backh=\"723\" data-backw=\"578\" data-imgfileid=\"100058692\" data-ratio=\"1.25\" data-s=\"300,640\" data-type=\"jpeg\" data-w=\"1080\" src=\"/static/res/logo/https://mmbiz.qpic.cn/mmbiz_jpg/A9b5Jxh1w2EMEZs7Epnibl3EbFkVPdvDwH54oWjkiaZ5iaJ2XaibdC7Bf5S8SULsogSEyw4OIDS946QLwwJ6XvhQAw/640?wx_fmt=jpeg&amp;from=appmsg&amp;tp=wxpic&amp;wxfrom=5&amp;wx_lazy=1\" style=\"width: 1080px !important;height: auto !important;visibility: visible !important;\" type=\"block\"/>\n     </section>\n     <p style=\"margin-bottom: 0px;line-height: 1.75em;text-align: center;\">\n      <span style=\"font-size: 16px;\">\n       <span mpa-font-style=\"mcn6399ry8e\" style=\"letter-spacing: 1px;font-size: 12px;\">\n        <span leaf=\"\">\n         <span style=\"color: rgb(136, 136, 136);\" textstyle=\"\">\n          图片来源：利物浦俱乐部社交媒体\n         </span>\n        </span>\n       </span>\n      </span>\n     </p>\n     <p style=\"margin-bottom: 0px;line-height: 1.75em;text-align: justify;\">\n      <span leaf=\"\" style=\"font-size: 16px;\">\n       <br/>\n      </span>\n     </p>\n     <p style=\"margin-bottom: 0px;line-height: 1.75em;text-align: justify;\">\n      <span leaf=\"\" style=\"font-size: 16px;\">\n       <span style=\"letter-spacing: 1px;\" textstyle=\"\">\n        国家队层面，若塔也是葡萄牙队的重要一员。在6月结束的欧洲国家联赛比赛中，他帮助葡萄牙队捧起了冠军奖杯。\n       </span>\n      </span>\n     </p>\n     <p style=\"margin-bottom: 0px;line-height: 1.75em;text-align: justify;\">\n      <span leaf=\"\" style=\"font-size: 16px;\">\n       <br/>\n      </span>\n     </p>\n     <p style=\"margin-bottom: 0px;line-height: 1.75em;text-align: justify;\">\n      <span leaf=\"\" style=\"font-size: 16px;\">\n       <span style=\"letter-spacing: 1px;\" textstyle=\"\">\n        6月22日，若塔刚刚与女友鲁特·卡尔多索完婚。两人自幼相识，堪称青梅竹马。卡尔多索当时在个人社交媒体写道：2025年6月22日，是的，永远。\n       </span>\n      </span>\n     </p>\n     <p style=\"margin-bottom: 0px;line-height: 1.75em;text-align: justify;\">\n      <span leaf=\"\" style=\"font-size: 16px;\">\n       <br/>\n      </span>\n     </p>\n     <section nodeleaf=\"\" style=\"margin-bottom: 0px;line-height: 1.75em;text-align: justify;\">\n      <img alt=\"图片\" class=\"rich_pages wxw-img js_insertlocalimg\" data-backh=\"767\" data-backw=\"578\" data-imgfileid=\"100058693\" data-ratio=\"1.3276661514683152\" data-s=\"300,640\" data-type=\"png\" data-w=\"647\" src=\"/static/res/logo/https://mmbiz.qpic.cn/mmbiz_png/A9b5Jxh1w2EMEZs7Epnibl3EbFkVPdvDwRECQiaUlLSEG8Daicgsa7rkiaic6LH2kA4YYFUICVMAFSYY0ZYS59to9nA/640?wx_fmt=png&amp;from=appmsg&amp;tp=wxpic&amp;wxfrom=5&amp;wx_lazy=1\" style=\"width: 1080px !important;height: auto !important;visibility: visible !important;\" type=\"block\"/>\n     </section>\n     <p style=\"margin-bottom: 0px;line-height: 1.75em;text-align: center;\">\n      <span style=\"font-size: 16px;\">\n       <span mpa-font-style=\"mcn62jaa85q\" style=\"letter-spacing: 1px;font-size: 12px;\">\n        <span leaf=\"\">\n         <span style=\"color: rgb(136, 136, 136);\" textstyle=\"\">\n          图片来源：若塔社交媒体\n         </span>\n        </span>\n       </span>\n      </span>\n     </p>\n     <p style=\"margin-bottom: 0px;line-height: 1.75em;text-align: justify;\">\n      <span leaf=\"\" style=\"font-size: 16px;\">\n       <br/>\n      </span>\n     </p>\n     <p style=\"margin-bottom: 0px;line-height: 1.75em;text-align: justify;\">\n      <span leaf=\"\" style=\"font-size: 16px;\">\n       <span style=\"letter-spacing: 1px;\" textstyle=\"\">\n        而就在昨天，若塔还更新了一则关于婚礼的视频，并配文：我们永远不会忘记的一天。\n       </span>\n      </span>\n     </p>\n     <p style=\"text-align: justify;line-height: 1.75em;\">\n      <font face=\"宋体\">\n       <span data-mpa-action-id=\"mch80w0yiw8\" leaf=\"\" style='color: rgba(0, 0, 0, 0.9);font-size: 16px;font-family: mp-quote, \"PingFang SC\", system-ui, -apple-system, BlinkMacSystemFont, \"Helvetica Neue\", \"Hiragino Sans GB\", \"Microsoft YaHei UI\", \"Microsoft YaHei\", Arial, sans-serif;letter-spacing: 0.034em;font-style: normal;font-weight: normal;'>\n        <br/>\n       </span>\n      </font>\n     </p>\n    </section>\n    <section class=\"mp_profile_iframe_wrp\" nodeleaf=\"\" style='-webkit-tap-highlight-color: transparent;margin-top: 0px;margin-bottom: 0px;padding: 0px;outline: 0px;max-width: 100%;box-sizing: border-box;color: rgba(0, 0, 0, 0.9);font-family: \"PingFang SC\", system-ui, -apple-system, BlinkMacSystemFont, \"Helvetica Neue\", \"Hiragino Sans GB\", \"Microsoft YaHei UI\", \"Microsoft YaHei\", Arial, sans-serif;font-size: 17px;font-style: normal;font-variant-ligatures: normal;font-variant-caps: normal;font-weight: 400;letter-spacing: 0.544px;orphans: 2;text-align: justify;text-indent: 0px;text-transform: none;widows: 2;word-spacing: 0px;-webkit-text-stroke-width: 0px;white-space: normal;background-color: rgb(255, 255, 255);text-decoration-thickness: initial;text-decoration-style: initial;text-decoration-color: initial;line-height: 1.75em;overflow-wrap: break-word !important;'>\n     <mp-common-profile class=\"js_uneditable custom_select_card mp_profile_iframe js_wx_tap_highlight\" data-alias=\"cns2012\" data-biz_account_status=\"0\" data-from=\"2\" data-headimg=\"http://mmbiz.qpic.cn/mmbiz_png/BIH6m4FJcJn8Frnv2d6HqFTpU77JE2D2mOhC8djIhibX35b1MZIbBNh12ib2ELEia2SqjDcefqicFl2KjiaXEGoBQGA/300?wx_fmt=png&amp;wxfrom=19\" data-id=\"MjM5ODA4OTIyMA==\" data-index=\"0\" data-is_biz_ban=\"0\" data-nickname=\"中国新闻网\" data-origin_num=\"4338\" data-pluginname=\"mpprofile\" data-service_type=\"0\" data-signature=\"新闻，有温度；分享，是力量！\" data-verify_status=\"3\">\n     </mp-common-profile>\n    </section>\n    <section style='-webkit-tap-highlight-color: transparent;margin-top: 0px;margin-bottom: 0px;padding: 0px;outline: 0px;max-width: 100%;color: rgba(0, 0, 0, 0.9);font-family: \"PingFang SC\", system-ui, -apple-system, BlinkMacSystemFont, \"Helvetica Neue\", \"Hiragino Sans GB\", \"Microsoft YaHei UI\", \"Microsoft YaHei\", Arial, sans-serif;font-size: 17px;font-style: normal;font-variant-ligatures: normal;font-variant-caps: normal;font-weight: 400;letter-spacing: 0.544px;orphans: 2;text-align: justify;text-indent: 0px;text-transform: none;widows: 2;word-spacing: 0px;-webkit-text-stroke-width: 0px;white-space: normal;background-color: rgb(255, 255, 255);text-decoration-thickness: initial;text-decoration-style: initial;text-decoration-color: initial;box-sizing: border-box !important;overflow-wrap: break-word !important;'>\n     <span leaf=\"\" style=\"-webkit-tap-highlight-color: transparent;margin-top: 0px;margin-bottom: 0px;padding: 0px;outline: 0px;max-width: 100%;box-sizing: border-box !important;overflow-wrap: break-word !important;\">\n      <br/>\n     </span>\n    </section>\n    <hr style='-webkit-tap-highlight-color: transparent;margin-top: 0px;margin-bottom: 0px;padding: 0px;outline: 0px;max-width: 100%;color: rgba(0, 0, 0, 0.9);font-family: \"PingFang SC\", system-ui, -apple-system, BlinkMacSystemFont, \"Helvetica Neue\", \"Hiragino Sans GB\", \"Microsoft YaHei UI\", \"Microsoft YaHei\", Arial, sans-serif;font-size: 17px;font-style: normal;font-variant-ligatures: normal;font-variant-caps: normal;font-weight: 400;orphans: 2;text-align: justify;text-indent: 0px;text-transform: none;widows: 2;word-spacing: 0px;-webkit-text-stroke-width: 0px;white-space: normal;background-color: rgb(255, 255, 255);text-decoration-thickness: initial;text-decoration-style: initial;text-decoration-color: initial;letter-spacing: 0.578px;border-style: solid;border-right-width: 0px;border-bottom-width: 0px;border-left-width: 0px;border-color: rgba(0, 0, 0, 0.1);transform-origin: 0px 0px;transform: scale(1, 0.5);box-sizing: border-box !important;overflow-wrap: break-word !important;'/>\n    <section style='-webkit-tap-highlight-color: transparent;margin-top: 0px;margin-bottom: 0px;padding: 0px;outline: 0px;max-width: 100%;color: rgba(0, 0, 0, 0.9);font-family: \"PingFang SC\", system-ui, -apple-system, BlinkMacSystemFont, \"Helvetica Neue\", \"Hiragino Sans GB\", \"Microsoft YaHei UI\", \"Microsoft YaHei\", Arial, sans-serif;font-size: 17px;font-style: normal;font-variant-ligatures: normal;font-variant-caps: normal;font-weight: 400;orphans: 2;text-align: justify;text-indent: 0px;text-transform: none;widows: 2;word-spacing: 0px;-webkit-text-stroke-width: 0px;white-space: normal;background-color: rgb(255, 255, 255);text-decoration-thickness: initial;text-decoration-style: initial;text-decoration-color: initial;letter-spacing: 0.578px;line-height: 1.75em;box-sizing: border-box !important;overflow-wrap: break-word !important;'>\n     <span style=\"-webkit-tap-highlight-color: transparent;margin-top: 0px;margin-bottom: 0px;padding: 0px;outline: 0px;max-width: 100%;color: rgb(136, 136, 136);font-size: 14px;letter-spacing: 1px;box-sizing: border-box !important;overflow-wrap: break-word !important;\">\n      <span leaf=\"\" style=\"-webkit-tap-highlight-color: transparent;margin-top: 0px;margin-bottom: 0px;padding: 0px;outline: 0px;max-width: 100%;box-sizing: border-box !important;overflow-wrap: break-word !important;\">\n       来源：中新体坛\n      </span>\n     </span>\n    </section>\n    <section style='-webkit-tap-highlight-color: transparent;margin-top: 0px;margin-bottom: 0px;padding: 0px;outline: 0px;max-width: 100%;color: rgba(0, 0, 0, 0.9);font-family: \"PingFang SC\", system-ui, -apple-system, BlinkMacSystemFont, \"Helvetica Neue\", \"Hiragino Sans GB\", \"Microsoft YaHei UI\", \"Microsoft YaHei\", Arial, sans-serif;font-size: 17px;font-style: normal;font-variant-ligatures: normal;font-variant-caps: normal;font-weight: 400;orphans: 2;text-align: justify;text-indent: 0px;text-transform: none;widows: 2;word-spacing: 0px;-webkit-text-stroke-width: 0px;white-space: normal;background-color: rgb(255, 255, 255);text-decoration-thickness: initial;text-decoration-style: initial;text-decoration-color: initial;letter-spacing: 0.578px;line-height: 1.75em;box-sizing: border-box !important;overflow-wrap: break-word !important;'>\n     <span style=\"-webkit-tap-highlight-color: transparent;margin-top: 0px;margin-bottom: 0px;padding: 0px;outline: 0px;max-width: 100%;color: rgb(136, 136, 136);font-size: 14px;letter-spacing: 1px;box-sizing: border-box !important;overflow-wrap: break-word !important;\">\n      <span leaf=\"\" style=\"-webkit-tap-highlight-color: transparent;margin-top: 0px;margin-bottom: 0px;padding: 0px;outline: 0px;max-width: 100%;box-sizing: border-box !important;overflow-wrap: break-word !important;\">\n       编辑：朴丽娜\n      </span>\n     </span>\n     <span leaf=\"\" style=\"-webkit-tap-highlight-color: transparent;margin-top: 0px;margin-bottom: 0px;padding: 0px;outline: 0px;max-width: 100%;box-sizing: border-box !important;overflow-wrap: break-word !important;\">\n      <br/>\n     </span>\n    </section>\n    <section data-pm-slice=\"3 7 []\" style='-webkit-tap-highlight-color: transparent;margin: 0px;padding: 0px;outline: 0px;max-width: 100%;color: rgba(0, 0, 0, 0.9);font-family: \"PingFang SC\", system-ui, -apple-system, BlinkMacSystemFont, \"Helvetica Neue\", \"Hiragino Sans GB\", \"Microsoft YaHei UI\", \"Microsoft YaHei\", Arial, sans-serif;font-size: 17px;font-style: normal;font-variant-ligatures: normal;font-variant-caps: normal;font-weight: 400;orphans: 2;text-align: justify;text-indent: 0px;text-transform: none;widows: 2;word-spacing: 0px;-webkit-text-stroke-width: 0px;white-space: normal;background-color: rgb(255, 255, 255);text-decoration-thickness: initial;text-decoration-style: initial;text-decoration-color: initial;letter-spacing: 0.578px;line-height: 1.75em;box-sizing: border-box !important;overflow-wrap: break-word !important;'>\n     <span style=\"-webkit-tap-highlight-color: transparent;margin-top: 0px;margin-bottom: 0px;padding: 0px;outline: 0px;max-width: 100%;letter-spacing: 1px;font-size: 14px;color: rgb(136, 136, 136);box-sizing: border-box !important;overflow-wrap: break-word !important;\">\n      <span leaf=\"\" style=\"-webkit-tap-highlight-color: transparent;margin-top: 0px;margin-bottom: 0px;padding: 0px;outline: 0px;max-width: 100%;box-sizing: border-box !important;overflow-wrap: break-word !important;\">\n       责编：赵一凡\n      </span>\n     </span>\n    </section>\n    <section style='-webkit-tap-highlight-color: transparent;margin: 0px 8px;padding: 0px;outline: 0px;max-width: 100%;box-sizing: border-box !important;overflow-wrap: break-word !important;color: rgba(0, 0, 0, 0.9);font-family: \"PingFang SC\", system-ui, -apple-system, BlinkMacSystemFont, \"Helvetica Neue\", \"Hiragino Sans GB\", \"Microsoft YaHei UI\", \"Microsoft YaHei\", Arial, sans-serif;font-size: 17px;font-style: normal;font-variant-ligatures: normal;font-variant-caps: normal;font-weight: 400;orphans: 2;text-align: justify;text-indent: 0px;text-transform: none;widows: 2;word-spacing: 0px;-webkit-text-stroke-width: 0px;white-space: normal;background-color: rgb(255, 255, 255);text-decoration-thickness: initial;text-decoration-style: initial;text-decoration-color: initial;letter-spacing: 0.578px;line-height: 1.75em;'>\n     <span style=\"-webkit-tap-highlight-color: transparent;margin: 0px;padding: 0px;outline: 0px;max-width: 100%;box-sizing: border-box !important;overflow-wrap: break-word !important;letter-spacing: 1px;font-size: 14px;color: rgb(136, 136, 136);\">\n      <span leaf=\"\" style=\"-webkit-tap-highlight-color: transparent;margin: 0px;padding: 0px;outline: 0px;max-width: 100%;box-sizing: border-box !important;overflow-wrap: break-word !important;\">\n       <img alt=\"图片\" class=\"rich_pages wxw-img\" data-imgfileid=\"505172334\" data-ratio=\"0.1259259259259259\" data-w=\"1080\" src=\"/static/res/logo/https://mmbiz.qpic.cn/sz_mmbiz_jpg/G4NzSjdbaJWXhSicoaJibs7axlKGLrf6Pp7ACZjJ5VGkxowNvwREnvrruvIqY5fY2jjez8aBtFxgLZicEHmtZVTcA/640?wx_fmt=other&amp;wxfrom=5&amp;wx_lazy=1&amp;wx_co=1&amp;tp=webp\" style='-webkit-tap-highlight-color: transparent;margin: 0px;padding: 0px;outline: 0px;max-width: 100%;box-sizing: border-box !important;overflow-wrap: break-word !important;vertical-align: bottom;height: auto !important;color: rgb(136, 136, 136);caret-color: rgba(0, 0, 0, 0);font-size: 16px;font-family: \"PingFang SC\", system-ui, -apple-system, BlinkMacSystemFont, \"Helvetica Neue\", \"Hiragino Sans GB\", \"Microsoft YaHei UI\", \"Microsoft YaHei\", Arial, sans-serif;background-color: rgb(255, 255, 255);border-style: none;letter-spacing: 0.544px;visibility: visible !important;width: 600.875px !important;'/>\n      </span>\n     </span>\n    </section>\n    <section class=\"channels_iframe_wrp\" nodeleaf=\"\">\n     <mp-common-videosnap class=\"js_uneditable custom_select_card channels_iframe videosnap_video_iframe videosnap_video_iframe\" data-authiconurl=\"http://dldir1.qq.com/weixin/checkresupdate/internet_news_media_auth_icon_38887ee9f6fe4639904638b28745b3f8.png\" data-desc=\"正值#高考报志愿季，致广大高考学子：选择学中医，你要面临什么？#中新健康\" data-headimgurl=\"http://wx.qlogo.cn/finderhead/CJ35Z2cnZA1SpkhbRtUEkpQvBWNnKfdDSAEvyeV4zWMiayyYKALv6xA/0\" data-height=\"1920\" data-id=\"export/UzFfAgtgekIEAQAAAAAA6Nks9O_MtgAAAAstQy6ubaLX4KHWvLEZgBPE8oBgaQs2NZaIzNPgMIv8SPsiW25YPcxNh__mtHWP\" data-nickname=\"中国新闻网\" data-nonceid=\"5452474230847708529\" data-pluginname=\"mpvideosnap\" data-type=\"video\" data-url=\"https://findermp.video.qq.com/251/20304/stodownload?encfilekey=rjD5jyTuFrIpZ2ibE8T7YmwgiahniaXswqzJLtvwPhY0PCsXgSmB1SkCR4dLf9KQLTktogOic5NdDuZ3hibG3e4FVVU3iaBKuwQ2icCDUNFSl8gqSD2Gkxxz4zIqA&amp;token=ic1n0xDG6awibVOyFbVCsEU7ryadERM0UafD8diaYFGva4HmrSMxBhNS0sLK8u2eV2AllEFP7Cssw7D9mm52iaia5cO3gxWibcuRI47VRlORQFVjHxiaRB0VUq3cVFL8AKZWXneYCSHqmWEz06u1lOvJSQXurLSWMYjBr89UAqmj8iaWUjk&amp;idx=1&amp;hy=SH&amp;m=&amp;scene=2&amp;uzid=1\" data-username=\"v2_060000231003b20faec8c6e78911cbd0c80cef30b0773c64654f54033b051646944bb8ae0159@finder\" data-width=\"1080\">\n     </mp-common-videosnap>\n    </section>\n    <section style='-webkit-tap-highlight-color: transparent;margin: 0px 8px;padding: 0px;outline: 0px;max-width: 100%;box-sizing: border-box !important;overflow-wrap: break-word !important;color: rgba(0, 0, 0, 0.9);font-family: \"PingFang SC\", system-ui, -apple-system, BlinkMacSystemFont, \"Helvetica Neue\", \"Hiragino Sans GB\", \"Microsoft YaHei UI\", \"Microsoft YaHei\", Arial, sans-serif;font-size: 17px;font-style: normal;font-variant-ligatures: normal;font-variant-caps: normal;font-weight: 400;orphans: 2;text-align: justify;text-indent: 0px;text-transform: none;widows: 2;word-spacing: 0px;-webkit-text-stroke-width: 0px;white-space: normal;background-color: rgb(255, 255, 255);text-decoration-thickness: initial;text-decoration-style: initial;text-decoration-color: initial;letter-spacing: 0.578px;line-height: 1.75em;'>\n     <span style=\"-webkit-tap-highlight-color: transparent;margin: 0px;padding: 0px;outline: 0px;max-width: 100%;box-sizing: border-box !important;overflow-wrap: break-word !important;letter-spacing: 1px;font-size: 14px;color: rgb(136, 136, 136);\">\n      <span leaf=\"\" style=\"-webkit-tap-highlight-color: transparent;margin: 0px;padding: 0px;outline: 0px;max-width: 100%;box-sizing: border-box !important;overflow-wrap: break-word !important;\">\n       <br/>\n      </span>\n     </span>\n    </section>\n    <section data-from=\"yb-recommend-list\" data-mpa-action-id=\"mcn0jabl1cia\" data-mpa-template=\"t\" data-pm-slice=\"0 0 []\">\n     <section data-from=\"yb-recommend\" data-mpa-template=\"t\" data-recommend-article-content-url=\"https://mp.weixin.qq.com/s/m16Vffu6X6NrAxYnkCaPiA\" data-recommend-article-cover=\"https://mmbiz.qpic.cn/mmbiz_jpg/BIH6m4FJcJnbMv3HicSPAKMXlB88kI8CECb6ywMzLbRaIf8MZHBiagPNvP0jkJScJ3OLzQMXwibSVoHng0S0B1HiaQ/0?wx_fmt=jpeg\" data-recommend-article-id=\"1000030061_1\" data-recommend-article-time=\"1751462572\" data-recommend-article-title=\"二孩奖励1万、三孩奖励2万，一次性到账！广东一地宣布\" data-recommend-article-type=\"normal\" data-recomment-template-id=\"1\">\n      <section data-mid=\"\" data-recommend-tid=\"1\" data-recommend-type=\"normal\" style=\"width: 100%;display: flex;justify-content: center;align-items: center;\">\n       <section data-mid=\"\" style=\"width: 100%;background: #ffffff;display: flex;justify-content: flex-start;align-items: center;flex-direction: column;\">\n        <section data-mid=\"\" style=\"width: 100%;display: flex;justify-content: center;align-items: center;\">\n         <span class=\"js_jump_icon h5_image_link\" style=\"width: 100%;flex:1;\">\n          <a data-itemshowtype=\"1\" data-linktype=\"1\" href=\"https://mp.weixin.qq.com/s?__biz=MjM5ODA4OTIyMA==&amp;mid=2652767575&amp;idx=1&amp;sn=bc02a7b0c37ab94d6dd98b7a89b55103&amp;scene=21#wechat_redirect\" linktype=\"image\" tab=\"innerlink\" target=\"_blank\">\n           <span leaf=\"\">\n            <img class=\"rich_pages wxw-img\" data-ratio=\"0.425\" data-w=\"1280\" src=\"/static/res/logo/https://mmbiz.qpic.cn/mmbiz_jpg/BIH6m4FJcJnbMv3HicSPAKMXlB88kI8CECb6ywMzLbRaIf8MZHBiagPNvP0jkJScJ3OLzQMXwibSVoHng0S0B1HiaQ/640?wx_fmt=jpeg\" style=\"width: 100%;max-height: none;object-fit: cover;\"/>\n           </span>\n          </a>\n         </span>\n        </section>\n        <section data-mid=\"\" style=\"width: 100%;padding: 9px 7px 8px;background: rgba(0, 0, 0, 0.65);font-size: 13px;font-weight: 400;color: #ffffff;line-height: 18px;margin-top: -35px;z-index: 20;\">\n         <p data-mid=\"\" data-recommend-title=\"t\">\n          <span leaf=\"\">\n           <a class=\"normal_text_link\" data-itemshowtype=\"0\" data-linktype=\"2\" href=\"https://mp.weixin.qq.com/s?__biz=MjM5ODA4OTIyMA==&amp;mid=2652767575&amp;idx=1&amp;sn=bc02a7b0c37ab94d6dd98b7a89b55103&amp;scene=21#wechat_redirect\" linktype=\"text\" style=\"color: rgb(255, 255, 255);\" target=\"_blank\" textvalue=\"\">\n            <span style=\"color: rgb(255, 255, 255);\" textstyle=\"\">\n             二孩奖励1万、三孩奖励2万，一次性到账！广东一地宣布\n            </span>\n           </a>\n          </span>\n         </p>\n        </section>\n       </section>\n      </section>\n     </section>\n     <section>\n      <span leaf=\"\">\n       <br/>\n      </span>\n     </section>\n     <section data-from=\"yb-recommend\" data-mpa-template=\"t\" data-recommend-article-content-url=\"https://mp.weixin.qq.com/s/5C-Skdc14VhkkXCOSDQazg\" data-recommend-article-cover=\"https://mmbiz.qpic.cn/mmbiz_jpg/BIH6m4FJcJnbMv3HicSPAKMXlB88kI8CEcjZLc1ibjtwLicqgKaunx0LO2nzbzsPqYfcAE6E6Psakv4t8BssdD4HQ/0?wx_fmt=jpeg\" data-recommend-article-id=\"1000030060_1\" data-recommend-article-time=\"1751457089\" data-recommend-article-title=\"宋某，不得录用为公务员\" data-recommend-article-type=\"normal\" data-recomment-template-id=\"1\">\n      <section data-mid=\"\" data-recommend-tid=\"1\" data-recommend-type=\"normal\" style=\"width: 100%;display: flex;justify-content: center;align-items: center;\">\n       <section data-mid=\"\" style=\"width: 100%;background: #ffffff;display: flex;justify-content: flex-start;align-items: center;flex-direction: column;\">\n        <section data-mid=\"\" style=\"width: 100%;display: flex;justify-content: center;align-items: center;\">\n         <span class=\"js_jump_icon h5_image_link\" style=\"width: 100%;flex:1;\">\n          <a data-itemshowtype=\"1\" data-linktype=\"1\" href=\"https://mp.weixin.qq.com/s?__biz=MjM5ODA4OTIyMA==&amp;mid=2652767560&amp;idx=1&amp;sn=f3477c31a6af034f8d385d24d996d657&amp;scene=21#wechat_redirect\" linktype=\"image\" tab=\"innerlink\" target=\"_blank\">\n           <span leaf=\"\">\n            <img class=\"rich_pages wxw-img\" data-ratio=\"0.42474916387959866\" data-w=\"897\" src=\"/static/res/logo/https://mmbiz.qpic.cn/mmbiz_jpg/BIH6m4FJcJnbMv3HicSPAKMXlB88kI8CEcjZLc1ibjtwLicqgKaunx0LO2nzbzsPqYfcAE6E6Psakv4t8BssdD4HQ/640?wx_fmt=jpeg\" style=\"width: 100%;max-height: none;object-fit: cover;\"/>\n           </span>\n          </a>\n         </span>\n        </section>\n        <section data-mid=\"\" style=\"width: 100%;padding: 9px 7px 8px;background: rgba(0, 0, 0, 0.65);font-size: 13px;font-weight: 400;color: #ffffff;line-height: 18px;margin-top: -35px;z-index: 20;\">\n         <p data-mid=\"\" data-recommend-title=\"t\">\n          <span leaf=\"\">\n           <a class=\"normal_text_link\" data-itemshowtype=\"0\" data-linktype=\"2\" href=\"https://mp.weixin.qq.com/s?__biz=MjM5ODA4OTIyMA==&amp;mid=2652767560&amp;idx=1&amp;sn=f3477c31a6af034f8d385d24d996d657&amp;scene=21#wechat_redirect\" linktype=\"text\" style=\"color: rgb(255, 255, 255);\" target=\"_blank\" textvalue=\"\">\n            <span style=\"color: rgb(255, 255, 255);\" textstyle=\"\">\n             宋某，不得录用为公务员\n            </span>\n           </a>\n          </span>\n         </p>\n        </section>\n       </section>\n      </section>\n     </section>\n     <section>\n      <span leaf=\"\">\n       <br/>\n      </span>\n     </section>\n     <section data-from=\"yb-recommend\" data-mpa-template=\"t\" data-recommend-article-content-url=\"https://mp.weixin.qq.com/s/ELxPyB_IB2MvbShERnqnVw\" data-recommend-article-cover=\"https://mmbiz.qpic.cn/mmbiz_jpg/BIH6m4FJcJlXpEnsn7Bwn7DadeND93pFSnFm6M75sybPZQeFHPp809CmcODaDM6fswAKS7uIa9etOMboRuIDWQ/0?wx_fmt=jpeg\" data-recommend-article-id=\"1000030052_1\" data-recommend-article-time=\"1751430358\" data-recommend-article-title=\"曾获破格提拔的曾芳，升任大学校长\" data-recommend-article-type=\"normal\" data-recomment-template-id=\"1\">\n      <section data-mid=\"\" data-recommend-tid=\"1\" data-recommend-type=\"normal\" style=\"width: 100%;display: flex;justify-content: center;align-items: center;\">\n       <section data-mid=\"\" style=\"width: 100%;background: #ffffff;display: flex;justify-content: flex-start;align-items: center;flex-direction: column;\">\n        <section data-mid=\"\" style=\"width: 100%;display: flex;justify-content: center;align-items: center;\">\n         <span class=\"js_jump_icon h5_image_link\" style=\"width: 100%;flex:1;\">\n          <a data-itemshowtype=\"1\" data-linktype=\"1\" href=\"https://mp.weixin.qq.com/s?__biz=MjM5ODA4OTIyMA==&amp;mid=2652767445&amp;idx=1&amp;sn=d36437bbed6b47d3f343b3c0f93ae926&amp;scene=21#wechat_redirect\" linktype=\"image\" tab=\"innerlink\" target=\"_blank\">\n           <span leaf=\"\">\n            <img class=\"rich_pages wxw-img\" data-ratio=\"0.42401960784313725\" data-w=\"816\" src=\"/static/res/logo/https://mmbiz.qpic.cn/mmbiz_jpg/BIH6m4FJcJlXpEnsn7Bwn7DadeND93pFSnFm6M75sybPZQeFHPp809CmcODaDM6fswAKS7uIa9etOMboRuIDWQ/640?wx_fmt=jpeg\" style=\"width: 100%;max-height: none;object-fit: cover;\"/>\n           </span>\n          </a>\n         </span>\n        </section>\n        <section data-mid=\"\" style=\"width: 100%;padding: 9px 7px 8px;background: rgba(0, 0, 0, 0.65);font-size: 13px;font-weight: 400;color: #ffffff;line-height: 18px;margin-top: -35px;z-index: 20;\">\n         <p data-mid=\"\" data-recommend-title=\"t\">\n          <span leaf=\"\">\n           <a class=\"normal_text_link\" data-itemshowtype=\"0\" data-linktype=\"2\" href=\"https://mp.weixin.qq.com/s?__biz=MjM5ODA4OTIyMA==&amp;mid=2652767445&amp;idx=1&amp;sn=d36437bbed6b47d3f343b3c0f93ae926&amp;scene=21#wechat_redirect\" linktype=\"text\" style=\"color: rgb(255, 255, 255);\" target=\"_blank\" textvalue=\"\">\n            <span style=\"color: rgb(255, 255, 255);\" textstyle=\"\">\n             曾获破格提拔的曾芳，升任大学校长\n            </span>\n           </a>\n          </span>\n         </p>\n        </section>\n       </section>\n      </section>\n     </section>\n    </section>\n   </section>\n  </section>\n </section>\n <p style=\"display: none;\">\n  <mp-style-type data-value=\"3\">\n  </mp-style-type>\n </p>\n</div>\n",
  "publish_time": 1751535354,
  "mp_id": "MP_WXS_2398089220",
  "pic_url": "https://mmbiz.qpic.cn/mmbiz_jpg/BIH6m4FJcJn7PHxoqd89xicMfDOzq1dGtrv3Qia6w1Fyq7bricJ3khT2PuiaY09okAqKqkvibHruo1lU8s9c5ylpXAg/0?wx_fmt=jpeg",
  "mp_name": "WeRss"
}